youtube_suggestions/__init__.py
youtube_suggestions/suggestions.py
youtube_suggestions-0.2.3.dist-info/METADATA
youtube_suggestions-0.2.3.dist-info/WHEEL
youtube_suggestions-0.2.3.dist-info/top_level.txt
youtube_suggestions-0.2.3.dist-info/RECORD
