Metadata-Version: 2.1
Name: youtube-suggestions
Version: 0.2.3
Summary: A package to get YouTube search suggestions with proxy support
Home-page: https://github.com/ryan-huang1/youtube_suggestions
Author: Ryan Huang
Author-email: ryan@stdint.com
Classifier: Development Status :: 3 - Alpha
Classifier: Intended Audience :: Developers
Classifier: License :: OSI Approved :: MIT License
Classifier: Operating System :: OS Independent
Classifier: Programming Language :: Python :: 3
Classifier: Programming Language :: Python :: 3.6
Classifier: Programming Language :: Python :: 3.7
Classifier: Programming Language :: Python :: 3.8
Classifier: Programming Language :: Python :: 3.9
Requires-Python: >=3.6
Requires-Dist: requests >=2.25.1
